README.md
setup.cfg
setup.py
cris_distribution_test_package.egg-info/PKG-INFO
cris_distribution_test_package.egg-info/SOURCES.txt
cris_distribution_test_package.egg-info/dependency_links.txt
cris_distribution_test_package.egg-info/not-zip-safe
cris_distribution_test_package.egg-info/top_level.txt
distributions/Binomialdistribution.py
distributions/Gaussiandistribution.py
distributions/Generaldistribution.py
distributions/__init__.py