Metadata-Version: 1.0
Name: cris-distribution-test-package
Version: 1.9
Summary: Gaussian and binomial distributions
Home-page: UNKNOWN
Author: UNKNOWN
Author-email: UNKNOWN
License: UNKNOWN
Platform: UNKNOWN
